voronoiville-0.1.0.dist-info/METADATA
voronoiville-0.1.0.dist-info/WHEEL
voronoiville-0.1.0.dist-info/license_files/LICENSE
voronoiville.libs/libgcc_s-4b50b6fc.so.1
voronoiville/__init__.py
voronoiville/__init__.pyi
voronoiville/py.typed
voronoiville/voronoiville.abi3.so
voronoiville-0.1.0.dist-info/RECORD
